[
 {
  "allow_on_submit": 0,
  "bold": 0,
  "collapsible": 0,
  "collapsible_depends_on": null,
  "columns": 0,
  "default": null,
  "depends_on": null,
  "description": null,
  "docstatus": 0,
  "doctype": "Custom Field",
  "dt": "Bank",
  "fetch_from": null,
  "fetch_if_empty": 0,
  "fieldname": "account",
  "fieldtype": "Link",
  "hidden": 0,
  "ignore_user_permissions": 0,
  "ignore_xss_filter": 0,
  "in_global_search": 0,
  "in_list_view": 0,
  "in_standard_filter": 0,
  "insert_after": "plaid_access_token",
  "label": "Account",
  "length": 0,
  "modified": "2019-11-22 15:17:24.873041",
  "name": "Bank-account",
  "no_copy": 0,
  "options": "Account",
  "parent": null,
  "parentfield": null,
  "parenttype": null,
  "permlevel": 0,
  "precision": "",
  "print_hide": 0,
  "print_hide_if_no_value": 0,
  "print_width": null,
  "read_only": 0,
  "report_hide": 0,
  "reqd": 0,
  "search_index": 0,
  "translatable": 0,
  "unique": 0,
  "width": null
 },
 {
  "allow_on_submit": 0,
  "bold": 0,
  "collapsible": 0,
  "collapsible_depends_on": null,
  "columns": 0,
  "default": null,
  "depends_on": null,
  "description": null,
  "docstatus": 0,
  "doctype": "Custom Field",
  "dt": "Sales Invoice",
  "fetch_from": null,
  "fetch_if_empty": 0,
  "fieldname": "tfy_transaction_type",
  "fieldtype": "Link",
  "hidden": 0,
  "ignore_user_permissions": 0,
  "ignore_xss_filter": 0,
  "in_global_search": 0,
  "in_list_view": 0,
  "in_standard_filter": 0,
  "insert_after": "due_date",
  "label": "Transaction Type",
  "length": 0,
  "modified": "2019-11-17 23:50:25.275388",
  "name": "Sales Invoice-tfy_transaction_type",
  "no_copy": 0,
  "options": "Transaction Type",
  "parent": null,
  "parentfield": null,
  "parenttype": null,
  "permlevel": 0,
  "precision": "",
  "print_hide": 0,
  "print_hide_if_no_value": 0,
  "print_width": null,
  "read_only": 0,
  "report_hide": 0,
  "reqd": 0,
  "search_index": 0,
  "translatable": 0,
  "unique": 0,
  "width": null
 },
 {
  "allow_on_submit": 0,
  "bold": 0,
  "collapsible": 0,
  "collapsible_depends_on": null,
  "columns": 0,
  "default": null,
  "depends_on": null,
  "description": null,
  "docstatus": 0,
  "doctype": "Custom Field",
  "dt": "Sales Invoice",
  "fetch_from": null,
  "fetch_if_empty": 0,
  "fieldname": "store_code",
  "fieldtype": "Data",
  "hidden": 0,
  "ignore_user_permissions": 0,
  "ignore_xss_filter": 0,
  "in_global_search": 0,
  "in_list_view": 0,
  "in_standard_filter": 0,
  "insert_after": "tfy_transaction_type",
  "label": "Store Code",
  "length": 0,
  "modified": "2019-11-22 16:59:57.737544",
  "name": "Sales Invoice-store_code",
  "no_copy": 0,
  "options": null,
  "parent": null,
  "parentfield": null,
  "parenttype": null,
  "permlevel": 0,
  "precision": "",
  "print_hide": 0,
  "print_hide_if_no_value": 0,
  "print_width": null,
  "read_only": 1,
  "report_hide": 0,
  "reqd": 0,
  "search_index": 0,
  "translatable": 1,
  "unique": 0,
  "width": null
 },
 {
  "allow_on_submit": 0,
  "bold": 0,
  "collapsible": 0,
  "collapsible_depends_on": null,
  "columns": 0,
  "default": null,
  "depends_on": null,
  "description": null,
  "docstatus": 0,
  "doctype": "Custom Field",
  "dt": "Sales Invoice",
  "fetch_from": null,
  "fetch_if_empty": 0,
  "fieldname": "auth_code",
  "fieldtype": "Data",
  "hidden": 0,
  "ignore_user_permissions": 0,
  "ignore_xss_filter": 0,
  "in_global_search": 0,
  "in_list_view": 0,
  "in_standard_filter": 0,
  "insert_after": "store_code",
  "label": "Auth Code",
  "length": 0,
  "modified": "2019-11-22 12:11:09.360901",
  "name": "Sales Invoice-auth_code",
  "no_copy": 0,
  "options": null,
  "parent": null,
  "parentfield": null,
  "parenttype": null,
  "permlevel": 0,
  "precision": "",
  "print_hide": 0,
  "print_hide_if_no_value": 0,
  "print_width": null,
  "read_only": 1,
  "report_hide": 0,
  "reqd": 0,
  "search_index": 0,
  "translatable": 1,
  "unique": 0,
  "width": null
 },
 {
  "allow_on_submit": 0,
  "bold": 0,
  "collapsible": 0,
  "collapsible_depends_on": null,
  "columns": 0,
  "default": null,
  "depends_on": null,
  "description": null,
  "docstatus": 0,
  "doctype": "Custom Field",
  "dt": "Sales Invoice",
  "fetch_from": null,
  "fetch_if_empty": 0,
  "fieldname": "credit_card_no",
  "fieldtype": "Data",
  "hidden": 0,
  "ignore_user_permissions": 0,
  "ignore_xss_filter": 0,
  "in_global_search": 0,
  "in_list_view": 0,
  "in_standard_filter": 0,
  "insert_after": "auth_code",
  "label": "Credit Card No",
  "length": 0,
  "modified": "2019-11-22 12:11:10.320510",
  "name": "Sales Invoice-credit_card_no",
  "no_copy": 0,
  "options": null,
  "parent": null,
  "parentfield": null,
  "parenttype": null,
  "permlevel": 0,
  "precision": "",
  "print_hide": 0,
  "print_hide_if_no_value": 0,
  "print_width": null,
  "read_only": 1,
  "report_hide": 0,
  "reqd": 0,
  "search_index": 0,
  "translatable": 1,
  "unique": 0,
  "width": null
 }
]